llama_gguf_quantizer/__init__.py
llama_gguf_quantizer/quantization.py
gguf_quantizer-0.1.dist-info/METADATA
gguf_quantizer-0.1.dist-info/WHEEL
gguf_quantizer-0.1.dist-info/entry_points.txt
gguf_quantizer-0.1.dist-info/top_level.txt
gguf_quantizer-0.1.dist-info/RECORD
