Metadata-Version: 2.1
Name: gguf-quantizer
Version: 0.1
Summary: A Python package for LLAMA gguf quantization
Author: Kirouane Ayoub
Author-email: ayoubkirouane3@email.com
